dartsclone-0.10.2.dist-info/WHEEL
dartsclone-0.10.2.dist-info/LICENSE
dartsclone-0.10.2.dist-info/METADATA
dartsclone-0.10.2.dist-info/top_level.txt
dartsclone-0.10.2.dist-info/RECORD
dartsclone/_dartsclone.cpython-36m-x86_64-linux-gnu.so
dartsclone/__init__.py
